vy_lambda_tools/__init__.py
vy_lambda_tools/configuration.py
vy_lambda_tools/feature_flag/__init__.py
vy_lambda_tools/feature_flag/base.py
vy_lambda_tools/feature_flag/providers.py
vy_lambda_tools/handlers/__init__.py
vy_lambda_tools/handlers/api_gateway.py
vy_lambda_tools/handlers/dynamodb.py
vy_lambda_tools/handlers/handler.py
vy_lambda_tools/handlers/sqs.py
vy_lambda_tools/instrumentation.py
vy_lambda_tools/py.typed
vy_lambda_tools/routing.py
vy_lambda_tools/test_helpers.py
vy_lambda_tools/types.py
vy_lambda_tools-0.5.1.dist-info/METADATA
vy_lambda_tools-0.5.1.dist-info/WHEEL
vy_lambda_tools-0.5.1.dist-info/RECORD
